{
  "actor": {
    "avatar_url": "https://avatars.githubusercontent.com/u/8041100?",
    "gravatar_id": "",
    "id": 8041100,
    "login": "local-minimum",
    "url": "https://api.github.com/users/local-minimum"
  },
  "created_at": "2018-06-18T08:41:33Z",
  "id": "7837991950",
  "org": {
    "avatar_url": "https://avatars.githubusercontent.com/u/29565481?",
    "id": 29565481,
    "login": "Scan-o-Matic",
    "url": "https://api.github.com/orgs/Scan-o-Matic"
  },
  "payload": {
    "before": "440e35e49326e51d09a990f26da613db87d29eb8",
    "commits": [
      {
        "author": {
          "email": "martin.zackrisson@molflow.com",
          "name": "Martin Zackrisson"
        },
        "distinct": true,
        "message": "Fixed type and test",
        "sha": "141a52d3a41f2818668e2160df6599ac3a3a26f5",
        "url": "https://api.github.com/repos/Scan-o-Matic/scanomatic/commits/141a52d3a41f2818668e2160df6599ac3a3a26f5"
      }
    ],
    "distinct_size": 1,
    "head": "141a52d3a41f2818668e2160df6599ac3a3a26f5",
    "push_id": 2652213175,
    "ref": "refs/heads/qc-qindex-integrate",
    "size": 1
  },
  "public": true,
  "repo": {
    "id": 33122681,
    "name": "Scan-o-Matic/scanomatic",
    "url": "https://api.github.com/repos/Scan-o-Matic/scanomatic"
  },
  "type": "PushEvent"
}