{
  "version": 7,
  "templating": {
    "list": [
      {
        "skipUrlSync": false,
        "allValue": null,
        "hide": 0,
        "multi": false,
        "includeAll": false,
        "options": [
          {
            "selected": false,
            "text": "Day",
            "value": "d"
          },
          {
            "text": "7 Days MA",
            "value": "d7",
            "selected": true
          },
          {
            "selected": false,
            "text": "Week",
            "value": "w"
          },
          {
            "selected": false,
            "text": "Month",
            "value": "m"
          },
          {
            "selected": false,
            "text": "Quarter",
            "value": "q"
          },
          {
            "text": "Year",
            "value": "y",
            "selected": false
          }
        ],
        "query": "d,w,m,q,y",
        "name": "period",
        "current": {
          "tags": [],
          "text": "7 Days MA",
          "value": "d7"
        },
        "label": "Period",
        "type": "custom"
      },
      {
        "hide": 0,
        "regex": "",
        "type": "query",
        "current": {
          "text": "All",
          "value": "$__all"
        },
        "skipUrlSync": false,
        "includeAll": true,
        "options": [],
        "query": "select '\"' || sig_mentions_texts_name || '\"' from tsig_mentions_texts order by 1",
        "tagValuesQuery": "",
        "useTags": false,
        "datasource": "psql",
        "multi": true,
        "sort": 0,
        "tagsQuery": "",
        "tags": [],
        "name": "sigs",
        "label": "SIG",
        "allValue": "",
        "refresh": 1
      },
      {
        "skipUrlSync": true,
        "hide": 2,
        "name": "full_name",
        "tags": [],
        "includeAll": false,
        "tagsQuery": "",
        "label": null,
        "tagValuesQuery": "",
        "current": {
          "value": "Kubernetes",
          "text": "Kubernetes"
        },
        "datasource": "psql",
        "type": "query",
        "regex": "",
        "query": "select value_s from gha_vars where name = 'full_name'",
        "multi": false,
        "options": [],
        "sort": 0,
        "useTags": false,
        "refresh": 1,
        "allValue": null
      },
      {
        "label": null,
        "useTags": false,
        "query": "select value_s from gha_vars where name = 'sig_mentions_docs_html'",
        "tagsQuery": "",
        "current": {
          "value": "\u003ch1 id=\"kubernetes-sig-mentions-dashboard\"\u003eKubernetes SIG mentions dashboard\u003c/h1\u003e\n\u003cp\u003eLinks:\u003c/p\u003e\n\u003cul\u003e\n\u003cli\u003ePostgres \u003ca href=\"https://github.com/cncf/devstats/blob/master/metrics/kubernetes/sig_mentions.sql\" target=\"_blank\"\u003eSQL file\u003c/a\u003e.\u003c/li\u003e\n\u003cli\u003eInfluxDB \u003ca href=\"https://github.com/cncf/devstats/blob/master/metrics/kubernetes/metrics.yaml#L246-L252\" target=\"_blank\"\u003eseries definition\u003c/a\u003e.\u003c/li\u003e\n\u003cli\u003eGrafana dashboard \u003ca href=\"https://github.com/cncf/devstats/blob/master/grafana/dashboards/kubernetes/sig_mentions.json\" target=\"_blank\"\u003eJSON\u003c/a\u003e.\u003c/li\u003e\n\u003cli\u003eDeveloper \u003ca href=\"https://github.com/cncf/devstats/blob/master/docs/dashboards/kubernetes/sig_mentions_devel.md\" target=\"_blank\"\u003edocumentation\u003c/a\u003e.\u003c/li\u003e\n\u003c/ul\u003e\n\u003ch1 id=\"description\"\u003eDescription\u003c/h1\u003e\n\u003cul\u003e\n\u003cli\u003eThis dashboard shows stacked number of various SIG mentions.\u003c/li\u003e\n\u003cli\u003eWe are getting SIG from all \u003cstrong\u003etexts\u003c/strong\u003e.\u003c/li\u003e\n\u003cli\u003eTo find a SIG we\u0026#39;re looking for texts like this \u003ccode\u003e@kubernetes/sig-SIG-kind\u003c/code\u003e, where kind can be: \u003cem\u003ebug, feature-request, pr-review, api-review, misc, proposal, design-proposal, test-failure\u003c/em\u003e.\u003c/li\u003e\n\u003cli\u003eFor example \u003ccode\u003e@kubernetes/sig-cluster-lifecycle-pr-review\u003c/code\u003e will evaluate to \u003ccode\u003ecluster-lifecycle\u003c/code\u003e.\u003c/li\u003e\n\u003cli\u003eKind part is optional, so \u003ccode\u003e@kubernetes/sig-node\u003c/code\u003e will evaluate to \u003ccode\u003enode\u003c/code\u003e.\u003c/li\u003e\n\u003cli\u003eThere can be other texts before and after the SIG, so \u003ccode\u003eHi there @kubernetes/sig-apps-feature-request, I want to ...\u003c/code\u003e will evaluate to \u003ccode\u003eapps\u003c/code\u003e.\u003c/li\u003e\n\u003cli\u003eFor exact \u003ccode\u003eregexp\u003c/code\u003e used, please check developer \u003ca href=\"https://github.com/cncf/devstats/blob/master/docs/dashboards/kubernetes/sig_mentions_devel.md\" target=\"_blank\"\u003edocumentation\u003c/a\u003e.\u003c/li\u003e\n\u003cli\u003e\u003cstrong\u003eTexts\u003c/strong\u003e means comments, commit messages, issue titles, issue texts, PR titles, PR texts, PR review texts.\u003c/li\u003e\n\u003cli\u003eYou can filter by period and SIG(s).\u003c/li\u003e\n\u003cli\u003eSelecting period (for example week) means that dahsboard will count SIG mentions in these periods.\u003c/li\u003e\n\u003cli\u003eSee \u003ca href=\"https://github.com/cncf/devstats/blob/master/docs/periods.md\" target=\"_blank\"\u003ehere\u003c/a\u003e for more informations about periods.\u003c/li\u003e\n\u003cli\u003eThis dashboard allows to select multiple SIG, it contains special \u0026#39;All\u0026#39; value to display all SIGs.\u003c/li\u003e\n\u003cli\u003eWe\u0026#39;re also excluding bots activity, see \u003ca href=\"https://github.com/cncf/devstats/blob/master/docs/excluding_bots.md\" target=\"_blank\"\u003eexcluding bots\u003c/a\u003e.\u003c/li\u003e\n\u003c/ul\u003e",
          "text": "\u003ch1 id=\"kubernetes-sig-mentions-dashboard\"\u003eKubernetes SIG mentions dashboard\u003c/h1\u003e\n\u003cp\u003eLinks:\u003c/p\u003e\n\u003cul\u003e\n\u003cli\u003ePostgres \u003ca href=\"https://github.com/cncf/devstats/blob/master/metrics/kubernetes/sig_mentions.sql\" target=\"_blank\"\u003eSQL file\u003c/a\u003e.\u003c/li\u003e\n\u003cli\u003eInfluxDB \u003ca href=\"https://github.com/cncf/devstats/blob/master/metrics/kubernetes/metrics.yaml#L246-L252\" target=\"_blank\"\u003eseries definition\u003c/a\u003e.\u003c/li\u003e\n\u003cli\u003eGrafana dashboard \u003ca href=\"https://github.com/cncf/devstats/blob/master/grafana/dashboards/kubernetes/sig_mentions.json\" target=\"_blank\"\u003eJSON\u003c/a\u003e.\u003c/li\u003e\n\u003cli\u003eDeveloper \u003ca href=\"https://github.com/cncf/devstats/blob/master/docs/dashboards/kubernetes/sig_mentions_devel.md\" target=\"_blank\"\u003edocumentation\u003c/a\u003e.\u003c/li\u003e\n\u003c/ul\u003e\n\u003ch1 id=\"description\"\u003eDescription\u003c/h1\u003e\n\u003cul\u003e\n\u003cli\u003eThis dashboard shows stacked number of various SIG mentions.\u003c/li\u003e\n\u003cli\u003eWe are getting SIG from all \u003cstrong\u003etexts\u003c/strong\u003e.\u003c/li\u003e\n\u003cli\u003eTo find a SIG we\u0026#39;re looking for texts like this \u003ccode\u003e@kubernetes/sig-SIG-kind\u003c/code\u003e, where kind can be: \u003cem\u003ebug, feature-request, pr-review, api-review, misc, proposal, design-proposal, test-failure\u003c/em\u003e.\u003c/li\u003e\n\u003cli\u003eFor example \u003ccode\u003e@kubernetes/sig-cluster-lifecycle-pr-review\u003c/code\u003e will evaluate to \u003ccode\u003ecluster-lifecycle\u003c/code\u003e.\u003c/li\u003e\n\u003cli\u003eKind part is optional, so \u003ccode\u003e@kubernetes/sig-node\u003c/code\u003e will evaluate to \u003ccode\u003enode\u003c/code\u003e.\u003c/li\u003e\n\u003cli\u003eThere can be other texts before and after the SIG, so \u003ccode\u003eHi there @kubernetes/sig-apps-feature-request, I want to ...\u003c/code\u003e will evaluate to \u003ccode\u003eapps\u003c/code\u003e.\u003c/li\u003e\n\u003cli\u003eFor exact \u003ccode\u003eregexp\u003c/code\u003e used, please check developer \u003ca href=\"https://github.com/cncf/devstats/blob/master/docs/dashboards/kubernetes/sig_mentions_devel.md\" target=\"_blank\"\u003edocumentation\u003c/a\u003e.\u003c/li\u003e\n\u003cli\u003e\u003cstrong\u003eTexts\u003c/strong\u003e means comments, commit messages, issue titles, issue texts, PR titles, PR texts, PR review texts.\u003c/li\u003e\n\u003cli\u003eYou can filter by period and SIG(s).\u003c/li\u003e\n\u003cli\u003eSelecting period (for example week) means that dahsboard will count SIG mentions in these periods.\u003c/li\u003e\n\u003cli\u003eSee \u003ca href=\"https://github.com/cncf/devstats/blob/master/docs/periods.md\" target=\"_blank\"\u003ehere\u003c/a\u003e for more informations about periods.\u003c/li\u003e\n\u003cli\u003eThis dashboard allows to select multiple SIG, it contains special \u0026#39;All\u0026#39; value to display all SIGs.\u003c/li\u003e\n\u003cli\u003eWe\u0026#39;re also excluding bots activity, see \u003ca href=\"https://github.com/cncf/devstats/blob/master/docs/excluding_bots.md\" target=\"_blank\"\u003eexcluding bots\u003c/a\u003e.\u003c/li\u003e\n\u003c/ul\u003e"
        },
        "skipUrlSync": true,
        "includeAll": false,
        "hide": 2,
        "type": "query",
        "datasource": "psql",
        "refresh": 1,
        "allValue": null,
        "name": "docs",
        "regex": "",
        "options": [],
        "sort": 0,
        "tagValuesQuery": "",
        "tags": [],
        "multi": false
      }
    ]
  },
  "annotations": {
    "list": [
      {
        "datasource": "-- Grafana --",
        "enable": true,
        "hide": true,
        "iconColor": "rgba(0, 211, 255, 1)",
        "name": "Annotations \u0026 Alerts",
        "type": "dashboard",
        "builtIn": 1
      },
      {
        "name": "Releases",
        "datasource": "psql",
        "showIn": 0,
        "textColumn": "",
        "rawQuery": "select extract(epoch from time) AS time, title as text, description as tags from sannotations where $__timeFilter(time)",
        "type": "alert",
        "enable": true,
        "iconColor": "rgba(255, 96, 96, 1)",
        "limit": 100,
        "query": "SELECT title, description from annotations WHERE $timeFilter order by time asc",
        "tagsColumn": "title,description",
        "titleColumn": "[[full_name]] release",
        "hide": false
      }
    ]
  },
  "time": {
    "from": "now-2y",
    "to": "now"
  },
  "editable": true,
  "graphTooltip": 0,
  "schemaVersion": 16,
  "timezone": "",
  "title": "SIG mentions",
  "tags": [
    "dashboard",
    "kubernetes",
    "SIGs"
  ],
  "gnetId": null,
  "links": [],
  "style": "dark",
  "id": 95,
  "uid": "41",
  "panels": [
    {
      "timeFrom": null,
      "xaxis": {
        "buckets": null,
        "mode": "time",
        "name": null,
        "show": true,
        "values": [
          "total"
        ]
      },
      "type": "graph",
      "nullPointMode": "null as zero",
      "points": false,
      "yaxes": [
        {
          "show": true,
          "format": "short",
          "label": "Mentions count",
          "logBase": 1,
          "max": null,
          "min": "0"
        },
        {
          "min": "0",
          "show": true,
          "format": "short",
          "label": "",
          "logBase": 1,
          "max": null
        }
      ],
      "dashes": false,
      "bars": true,
      "id": 1,
      "decimals": 2,
      "lines": false,
      "stack": true,
      "steppedLine": false,
      "fill": 1,
      "spaceLength": 10,
      "tooltip": {
        "shared": true,
        "sort": 2,
        "value_type": "individual"
      },
      "renderer": "flot",
      "yaxis": {
        "alignLevel": null,
        "align": false
      },
      "thresholds": [],
      "dashLength": 10,
      "transparent": true,
      "title": "SIG mentions (using text, [[period]])",
      "aliasColors": {
        
      },
      "percentage": false,
      "pointradius": 5,
      "gridPos": {
        "w": 24,
        "x": 0,
        "y": 0,
        "h": 21
      },
      "targets": [
        {
          "orderByTime": "ASC",
          "dsType": "influxdb",
          "format": "time_series",
          "resultFormat": "time_series",
          "tags": [],
          "measurement": "sig_federation_d",
          "policy": "default",
          "rawQuery": true,
          "query": "SELECT /^[[sigs]]$/ FROM \"sig_mentions_texts_[[period]]\" WHERE $timeFilter",
          "rawSql": "select\n  time,\n  ${sigs:csv}\nfrom\n  ssigm_txt\nwhere\n  $__timeFilter(time)\n  and period = '[[period]]'\norder by\n  time",
          "groupBy": [],
          "refId": "A",
          "select": [
            [
              {
                "type": "field",
                "params": [
                  "value"
                ]
              }
            ]
          ],
          "alias": ""
        }
      ],
      "datasource": "psql",
      "legend": {
        "alignAsTable": true,
        "avg": true,
        "hideEmpty": false,
        "hideZero": false,
        "sort": "avg",
        "total": true,
        "max": true,
        "min": true,
        "current": true,
        "rightSide": true,
        "show": true,
        "sortDesc": true,
        "values": true
      },
      "timeShift": null,
      "links": [],
      "description": "Shows how often various SIG (software interest groups) have been mentioned in comments, issues, PRs",
      "linewidth": 1,
      "seriesOverrides": []
    },
    {
      "title": "Dashboard documentation",
      "type": "text",
      "content": "${docs:raw}",
      "gridPos": {
        "x": 0,
        "y": 21,
        "h": 13,
        "w": 24
      },
      "id": 3,
      "links": [],
      "mode": "html"
    }
  ],
  "timepicker": {
    "refresh_intervals": [
      "5s",
      "10s",
      "30s",
      "1m",
      "5m",
      "15m",
      "30m",
      "1h",
      "2h",
      "1d"
    ],
    "time_options": [
      "5m",
      "15m",
      "1h",
      "6h",
      "12h",
      "24h",
      "2d",
      "7d",
      "30d"
    ]
  }
}